{
    "avg": {
        "wmc": 7.93,
        "ccn": 4.4,
        "bugs": 0.17,
        "kanDefect": 0.39,
        "relativeSystemComplexity": 97.36,
        "relativeDataComplexity": 1.89,
        "relativeStructuralComplexity": 95.47,
        "volume": 499.49,
        "commentWeight": 35.43,
        "intelligentContent": 87.36,
        "lcom": 1.4,
        "instability": 0.65,
        "afferentCoupling": 1.33,
        "efferentCoupling": 2.87,
        "difficulty": 8.34,
        "mi": 90.72,
        "distance": 0.32,
        "incomingCDep": 1.2,
        "incomingPDep": 0.8,
        "outgoingCDep": 3.4,
        "outgoingPDep": 2.4,
        "classesPerPackage": 3
    },
    "sum": {
        "loc": 1089,
        "cloc": 364,
        "lloc": 726,
        "nbMethods": 68,
        "nbClasses": 15,
        "nbInterfaces": 0,
        "nbPackages": 5,
        "violations": {
            "total": 4,
            "information": 0,
            "warning": 4,
            "error": 0,
            "critical": 0
        }
    }
}